swing_schedule/__init__.py
swing_schedule/swing_schedule.py
swing_schedule/data/teachers.csv
swing_schedule-0.1.1.dist-info/METADATA
swing_schedule-0.1.1.dist-info/WHEEL
swing_schedule-0.1.1.dist-info/entry_points.txt
swing_schedule-0.1.1.dist-info/licenses/LICENSE
swing_schedule-0.1.1.dist-info/RECORD
