Metadata-Version: 2.4
Name: swing-schedule
Version: 0.1.1
Summary: Swing Dance Schedule Generator
Project-URL: Repository, https://github.com/ep69/swing-schedule
License-File: LICENSE
Requires-Python: >=3.13
Requires-Dist: ortools>=9.12
